Workbook
Name aport: Khon_Invest!$E$17
Name patrim_total: Khon_Invest!$E$20
Name periodo_ano: Khon_Invest!$E$18
Name tx_carteira: Khon_Invest!$E$13

Sheet Khon_Invest
C11: CONFIGURAÇÕES
C12: Salário Mensal | E12: 3000
C13: Rendimento da Carteira | E13: 0.01
C14: Sugestão de Investimento (30%) | E14: =$E$12*30% -> 900
C16: INVESTIMENTO MENSAL
C17: Quanto investir por mês? | E17: 500
C18: Por quantos anos? | E18: 3
C19: Taxa de rendimento mensal? | E19: =tx_carteira -> 0.01
C20: Patrimônio Acumulado? | E20: =FV(tx_carteira,periodo_ano*12,aport*-1) -> 21538.439
C21: Dividendo mensais? | E21: =patrim_total*tx_carteira -> 215.38439
C22: CENÁRIO MENSAL | E22: DIVIDENDOS
B23: 5 | C23: Quanto em 5 anos? | D23: =FV(tx_carteira,$B23*12,aport*-1) -> 40834.835 | E23: =$D23*tx_carteira -> 408.34835
B24: 10 | C24: Quanto em 10 anos? | D24: =FV(tx_carteira,$B24*12,aport*-1) -> 115019.34 | E24: =$D24*tx_carteira -> 1150.1934
B25: 20 | C25: Quanto em 20 anos? | D25: =FV(tx_carteira,$B25*12,aport*-1) -> 494627.68 | E25: =$D25*tx_carteira -> 4946.2768
B26: 30 | C26: Quanto em 30 anos? | D26: =FV(tx_carteira,$B26*12,aport*-1) -> 1747482.1 | E26: =$D26*tx_carteira -> 17474.821
C29: PERFIL | E29: Agressivo
C30: VALOR A SER INVESTIDO POR MÊS | E30: =aport -> 500
C31: TIPOS DE FIIS | D31: PERCENTUAL SUGERIDO | E31: VALORES SUGERIDOS
C32: PAPEL | D32: =VLOOKUP($E$29&"-"&C32,tb_ref!$A$1:$D$20,4,FALSE) -> 0.5 | E32: =$E$30*D32 -> 250
C33: TIJOLO | D33: =VLOOKUP($E$29&"-"&C33,tb_ref!$A$1:$D$20,4,FALSE) -> 0.1 | E33: =$E$30*D33 -> 50
C34: HÍBRIDOS | D34: =VLOOKUP($E$29&"-"&C34,tb_ref!$A$1:$D$20,4,FALSE) -> 0.05 | E34: =$E$30*D34 -> 25
C35: FOFs | D35: =VLOOKUP($E$29&"-"&C35,tb_ref!$A$1:$D$20,4,FALSE) -> 0.05 | E35: =$E$30*D35 -> 25
C36: DESENVOLVIMENTO | D36: =VLOOKUP($E$29&"-"&C36,tb_ref!$A$1:$D$20,4,FALSE) -> 0.2 | E36: =$E$30*D36 -> 100
C37: HOTELARIAS | D37: =VLOOKUP($E$29&"-"&C37,tb_ref!$A$1:$D$20,4,FALSE) -> 0.1 | E37: =$E$30*D37 -> 50
C38: TOTAL | D38: =SUM(D32:D37) -> 1 | E38: =SUM(E32:E37) -> 500

Sheet tb_ref
A2: ID | B2: Perfil | C2: TIPOS DE FIIS | D2: %
A3: =B3&"-"&C3 -> Conservador-PAPEL | B3: Conservador | C3: PAPEL | D3: 0.3
A4: =B4&"-"&C4 -> Conservador-TIJOLO | B4: Conservador | C4: TIJOLO | D4: 0.5
A5: =B5&"-"&C5 -> Conservador-HÍBRIDOS | B5: Conservador | C5: HÍBRIDOS | D5: 0.1
A6: =B6&"-"&C6 -> Conservador-FOFs | B6: Conservador | C6: FOFs | D6: 0.1
A7: =B7&"-"&C7 -> Conservador-DESENVOLVIMENTO | B7: Conservador | C7: DESENVOLVIMENTO | D7: 0
A8: =B8&"-"&C8 -> Conservador-HOTELARIAS | B8: Conservador | C8: HOTELARIAS | D8: 0
A9: =B9&"-"&C9 -> Agressivo-PAPEL | B9: Agressivo | C9: PAPEL | D9: 0.5
A10: =B10&"-"&C10 -> Agressivo-TIJOLO | B10: Agressivo | C10: TIJOLO | D10: 0.1
A11: =B11&"-"&C11 -> Agressivo-HÍBRIDOS | B11: Agressivo | C11: HÍBRIDOS | D11: 0.05
A12: =B12&"-"&C12 -> Agressivo-FOFs | B12: Agressivo | C12: FOFs | D12: 0.05
A13: =B13&"-"&C13 -> Agressivo-DESENVOLVIMENTO | B13: Agressivo | C13: DESENVOLVIMENTO | D13: 0.2
A14: =B14&"-"&C14 -> Agressivo-HOTELARIAS | B14: Agressivo | C14: HOTELARIAS | D14: 0.1
... A20: =B20&"-"&C20 -> Moderado-HOTELARIAS | B20: Moderado | C20: HOTELARIAS | D20: 0.1
